controller_hub.py
maya_controller_hub-0.1.2.dist-info/LICENSE
maya_controller_hub-0.1.2.dist-info/METADATA
maya_controller_hub-0.1.2.dist-info/WHEEL
maya_controller_hub-0.1.2.dist-info/top_level.txt
maya_controller_hub-0.1.2.dist-info/RECORD
