Metadata-Version: 2.1
Name: maya-controller-hub
Version: 0.1.2
Summary: Maya控制器库实现
Author-email: cpcgskill <cpcgskill@outlook.com>
License: Apache Software License (Apache 2.0)
Project-URL: Homepage, https://github.com/cpcgskill/maya-controller-hub
Project-URL: Bug Tracker, https://github.com/cpcgskill/maya-controller-hub/issues
Classifier: License :: OSI Approved :: Apache Software License
Classifier: Programming Language :: Python
Classifier: Programming Language :: Python :: 2
Classifier: Programming Language :: Python :: 2.7
Classifier: Programming Language :: Python :: 3
Classifier: Programming Language :: Python :: 3.6
Classifier: Programming Language :: Python :: 3.7
Classifier: Programming Language :: Python :: 3.8
Classifier: Programming Language :: Python :: 3.9
Classifier: Programming Language :: Python :: 3.10
Classifier: Programming Language :: Python :: Implementation :: CPython
Requires-Python: !=3.0.*,!=3.1.*,!=3.2.*,!=3.3.*,!=3.4.*,!=3.5.*,>=2.7
License-File: LICENSE
Requires-Dist: cpmel>=1.0
Requires-Dist: maya-rig-core>=0.2
